PyHard/__init__.py
PyHard/core.py
PyHard/models.py
dwpyhard-0.0.0.0.3.dist-info/licenses/LICENSE
dwpyhard-0.0.0.0.3.dist-info/METADATA
dwpyhard-0.0.0.0.3.dist-info/WHEEL
dwpyhard-0.0.0.0.3.dist-info/top_level.txt
dwpyhard-0.0.0.0.3.dist-info/RECORD
